kato/__init__.py
kato/kato.py
kato-1.0.0.dist-info/LICENSE
kato-1.0.0.dist-info/METADATA
kato-1.0.0.dist-info/WHEEL
kato-1.0.0.dist-info/top_level.txt
kato-1.0.0.dist-info/RECORD
