Metadata-Version: 2.1
Name: kato
Version: 1.0.0
Summary: NetCloud24 Cryptographic POC
Home-page: https://github.com/ameasere/kato
Author: ameasere
Author-email: leigh@ameasere.com
Classifier: Programming Language :: Python
Classifier: Operating System :: OS Independent
License-File: LICENSE
Requires-Dist: aeskeyschedule
